{
  "ticker": "SJM",
  "last_updated": "2026-06-14T10:55:30.174794",
  "retention_years": 3,
  "count": 6,
  "transactions": [
    {
      "id": 402,
      "issuer_name": "J M SMUCKER Co",
      "reporting_owner": "Penrose Jill R",
      "reporting_owner_cik": "0001611898",
      "reporting_owner_position": "Chief People Officer",
      "transaction_date": "2026-06-11",
      "transaction_shares": "5978",
      "transaction_price": "0",
      "transaction_type": "A",
      "shares_after_transaction": "21774"
    },
    {
      "id": 403,
      "issuer_name": "J M SMUCKER Co",
      "reporting_owner": "Ferguson Robert D",
      "reporting_owner_cik": "0002110430",
      "reporting_owner_position": "Chief Product Supply Officer",
      "transaction_date": "2026-06-11",
      "transaction_shares": "8650",
      "transaction_price": "0",
      "transaction_type": "A",
      "shares_after_transaction": "40076"
    },
    {
      "id": 404,
      "issuer_name": "J M SMUCKER Co",
      "reporting_owner": "Marshall Tucker H",
      "reporting_owner_cik": "0001810809",
      "reporting_owner_position": "Chief Financial Officer",
      "transaction_date": "2026-06-11",
      "transaction_shares": "9207",
      "transaction_price": "0",
      "transaction_type": "A",
      "shares_after_transaction": "43802"
    },
    {
      "id": 405,
      "issuer_name": "J M SMUCKER Co",
      "reporting_owner": "SMUCKER MARK T",
      "reporting_owner_cik": "0001251544",
      "reporting_owner_position": "CEO, Chair of Board",
      "transaction_date": "2026-06-11",
      "transaction_shares": "34497",
      "transaction_price": "0",
      "transaction_type": "A",
      "shares_after_transaction": "107686"
    },
    {
      "id": 406,
      "issuer_name": "J M SMUCKER Co",
      "reporting_owner": "Knudsen Jeannette L",
      "reporting_owner_cik": "0001463366",
      "reporting_owner_position": "Chief Legal Officer",
      "transaction_date": "2026-06-11",
      "transaction_shares": "5550",
      "transaction_price": "116.29",
      "transaction_type": "S",
      "shares_after_transaction": "16039"
    },
    {
      "id": 407,
      "issuer_name": "J M SMUCKER Co",
      "reporting_owner": "Williams Katherine Marie",
      "reporting_owner_cik": "0002115429",
      "reporting_owner_position": "Chief Marketing Officer",
      "transaction_date": "2026-06-11",
      "transaction_shares": "3136",
      "transaction_price": "0",
      "transaction_type": "A",
      "shares_after_transaction": "12848"
    }
  ]
}