{
  "ticker": "BRK.A",
  "last_updated": "2025-08-13T08:34:01.107744",
  "retention_years": 3,
  "count": 1,
  "transactions": [
    {
      "id": 191,
      "issuer_name": "BERKSHIRE HATHAWAY INC",
      "reporting_owner": "Jain Ajit",
      "reporting_owner_cik": "0001728451",
      "reporting_owner_position": "Vice Chairman",
      "transaction_date": "2025-08-08",
      "transaction_shares": "2000",
      "transaction_price": "464.726",
      "transaction_type": "S",
      "shares_after_transaction": "122308"
    }
  ]
}