{
  "ticker": "DLR",
  "year": 2024,
  "quarter": 3,
  "last_updated": "2025-04-19T08:33:46.038115",
  "count": 14,
  "transactions": [
    {
      "id": 98563,
      "issuer_name": "DIGITAL REALTY TRUST, INC.",
      "reporting_owner": "Lee Jeannie",
      "reporting_owner_cik": "0001926524",
      "reporting_owner_position": "EVP, GENERAL COUNSEL",
      "transaction_date": "2024-08-23",
      "transaction_shares": "2",
      "transaction_price": "152.18",
      "transaction_type": "F",
      "shares_after_transaction": "10755"
    },
    {
      "id": 123718,
      "issuer_name": "DIGITAL REALTY TRUST, INC.",
      "reporting_owner": "Lee Jeannie",
      "reporting_owner_cik": "0001926524",
      "reporting_owner_position": "EVP, GENERAL COUNSEL",
      "transaction_date": "2024-08-23",
      "transaction_shares": "2",
      "transaction_price": "152.18",
      "transaction_type": "F",
      "shares_after_transaction": "10755"
    },
    {
      "id": 150855,
      "issuer_name": "DIGITAL REALTY TRUST, INC.",
      "reporting_owner": "Lee Jeannie",
      "reporting_owner_cik": "0001926524",
      "reporting_owner_position": "EVP, GENERAL COUNSEL",
      "transaction_date": "2024-08-23",
      "transaction_shares": "2",
      "transaction_price": "152.18",
      "transaction_type": "F",
      "shares_after_transaction": "10755"
    },
    {
      "id": 98578,
      "issuer_name": "DIGITAL REALTY TRUST, INC.",
      "reporting_owner": "MANDEVILLE JEAN F H P",
      "reporting_owner_cik": "0001219934",
      "reporting_owner_position": null,
      "transaction_date": "2024-08-01",
      "transaction_shares": "600",
      "transaction_price": "150.26",
      "transaction_type": "S",
      "shares_after_transaction": "9055"
    },
    {
      "id": 123733,
      "issuer_name": "DIGITAL REALTY TRUST, INC.",
      "reporting_owner": "MANDEVILLE JEAN F H P",
      "reporting_owner_cik": "0001219934",
      "reporting_owner_position": null,
      "transaction_date": "2024-08-01",
      "transaction_shares": "600",
      "transaction_price": "150.26",
      "transaction_type": "S",
      "shares_after_transaction": "9055"
    },
    {
      "id": 150871,
      "issuer_name": "DIGITAL REALTY TRUST, INC.",
      "reporting_owner": "MANDEVILLE JEAN F H P",
      "reporting_owner_cik": "0001219934",
      "reporting_owner_position": null,
      "transaction_date": "2024-08-01",
      "transaction_shares": "600",
      "transaction_price": "150.26",
      "transaction_type": "S",
      "shares_after_transaction": "9055"
    },
    {
      "id": 75551,
      "issuer_name": "DIGITAL REALTY TRUST, INC.",
      "reporting_owner": "Kornegay Christine Beseda",
      "reporting_owner_cik": "0001392404",
      "reporting_owner_position": "CHIEF ACCOUNTING OFFICER",
      "transaction_date": "2024-07-01",
      "transaction_shares": "19",
      "transaction_price": "152.13",
      "transaction_type": "F",
      "shares_after_transaction": "1256"
    },
    {
      "id": 75567,
      "issuer_name": "DIGITAL REALTY TRUST, INC.",
      "reporting_owner": "Lee Jeannie",
      "reporting_owner_cik": "0001926524",
      "reporting_owner_position": "EVP, GENERAL COUNSEL",
      "transaction_date": "2024-07-01",
      "transaction_shares": "10",
      "transaction_price": "152.13",
      "transaction_type": "F",
      "shares_after_transaction": "10757"
    },
    {
      "id": 98564,
      "issuer_name": "DIGITAL REALTY TRUST, INC.",
      "reporting_owner": "Kornegay Christine Beseda",
      "reporting_owner_cik": "0001392404",
      "reporting_owner_position": "CHIEF ACCOUNTING OFFICER",
      "transaction_date": "2024-07-01",
      "transaction_shares": "19",
      "transaction_price": "152.13",
      "transaction_type": "F",
      "shares_after_transaction": "1256"
    },
    {
      "id": 98581,
      "issuer_name": "DIGITAL REALTY TRUST, INC.",
      "reporting_owner": "Lee Jeannie",
      "reporting_owner_cik": "0001926524",
      "reporting_owner_position": "EVP, GENERAL COUNSEL",
      "transaction_date": "2024-07-01",
      "transaction_shares": "10",
      "transaction_price": "152.13",
      "transaction_type": "F",
      "shares_after_transaction": "10757"
    },
    {
      "id": 123719,
      "issuer_name": "DIGITAL REALTY TRUST, INC.",
      "reporting_owner": "Kornegay Christine Beseda",
      "reporting_owner_cik": "0001392404",
      "reporting_owner_position": "CHIEF ACCOUNTING OFFICER",
      "transaction_date": "2024-07-01",
      "transaction_shares": "19",
      "transaction_price": "152.13",
      "transaction_type": "F",
      "shares_after_transaction": "1256"
    },
    {
      "id": 123736,
      "issuer_name": "DIGITAL REALTY TRUST, INC.",
      "reporting_owner": "Lee Jeannie",
      "reporting_owner_cik": "0001926524",
      "reporting_owner_position": "EVP, GENERAL COUNSEL",
      "transaction_date": "2024-07-01",
      "transaction_shares": "10",
      "transaction_price": "152.13",
      "transaction_type": "F",
      "shares_after_transaction": "10757"
    },
    {
      "id": 150856,
      "issuer_name": "DIGITAL REALTY TRUST, INC.",
      "reporting_owner": "Kornegay Christine Beseda",
      "reporting_owner_cik": "0001392404",
      "reporting_owner_position": "CHIEF ACCOUNTING OFFICER",
      "transaction_date": "2024-07-01",
      "transaction_shares": "19",
      "transaction_price": "152.13",
      "transaction_type": "F",
      "shares_after_transaction": "1256"
    },
    {
      "id": 150875,
      "issuer_name": "DIGITAL REALTY TRUST, INC.",
      "reporting_owner": "Lee Jeannie",
      "reporting_owner_cik": "0001926524",
      "reporting_owner_position": "EVP, GENERAL COUNSEL",
      "transaction_date": "2024-07-01",
      "transaction_shares": "10",
      "transaction_price": "152.13",
      "transaction_type": "F",
      "shares_after_transaction": "10757"
    }
  ]
}