{
  "ticker": "CME",
  "year": 2024,
  "quarter": 2,
  "last_updated": "2025-04-19T07:36:40.944791",
  "count": 5,
  "transactions": [
    {
      "id": 40899,
      "issuer_name": "CME GROUP INC.",
      "reporting_owner": "Cook Elizabeth A",
      "reporting_owner_cik": "0001643475",
      "reporting_owner_position": null,
      "transaction_date": "2024-05-20",
      "transaction_shares": "1000",
      "transaction_price": "211.52",
      "transaction_type": "S",
      "shares_after_transaction": "18241"
    },
    {
      "id": 40909,
      "issuer_name": "CME GROUP INC.",
      "reporting_owner": "Sammann Derek",
      "reporting_owner_cik": "0001475318",
      "reporting_owner_position": "Sr MD Gl Hd Commodity & Option",
      "transaction_date": "2024-05-14",
      "transaction_shares": "3789",
      "transaction_price": "0",
      "transaction_type": "G",
      "shares_after_transaction": "9694"
    },
    {
      "id": 40914,
      "issuer_name": "CME GROUP INC.",
      "reporting_owner": "SAVAGE TERRY L",
      "reporting_owner_cik": "0001094549",
      "reporting_owner_position": null,
      "transaction_date": "2024-05-13",
      "transaction_shares": "2500",
      "transaction_price": "210.6479",
      "transaction_type": "S",
      "shares_after_transaction": "17441"
    },
    {
      "id": 40901,
      "issuer_name": "CME GROUP INC.",
      "reporting_owner": "Piell Hilda Harris",
      "reporting_owner_cik": "0001409789",
      "reporting_owner_position": "Sr MD & Chief HR Officer",
      "transaction_date": "2024-05-08",
      "transaction_shares": "300",
      "transaction_price": "210.40",
      "transaction_type": "S",
      "shares_after_transaction": "36096"
    },
    {
      "id": 40897,
      "issuer_name": "CME GROUP INC.",
      "reporting_owner": "DUFFY TERRENCE A",
      "reporting_owner_cik": "0001212809",
      "reporting_owner_position": "Chairman and CEO",
      "transaction_date": "2024-04-29",
      "transaction_shares": "4076",
      "transaction_price": "209.52",
      "transaction_type": "S",
      "shares_after_transaction": "103379"
    }
  ]
}