{
  "ticker": "FIS",
  "year": 2024,
  "quarter": 4,
  "last_updated": "2025-04-19T09:55:23.615356",
  "count": 21,
  "transactions": [
    {
      "id": 168714,
      "issuer_name": "Fidelity National Information Services, Inc.",
      "reporting_owner": "Williams Lenore D",
      "reporting_owner_cik": "0001730708",
      "reporting_owner_position": "CEVP, Chief People Officer",
      "transaction_date": "2024-11-15",
      "transaction_shares": "11305",
      "transaction_price": "87.97",
      "transaction_type": "S",
      "shares_after_transaction": "32198.9308"
    },
    {
      "id": 199657,
      "issuer_name": "Fidelity National Information Services, Inc.",
      "reporting_owner": "Williams Lenore D",
      "reporting_owner_cik": "0001730708",
      "reporting_owner_position": "CEVP, Chief People Officer",
      "transaction_date": "2024-11-15",
      "transaction_shares": "11305",
      "transaction_price": "87.97",
      "transaction_type": "S",
      "shares_after_transaction": "32198.9308"
    },
    {
      "id": 232860,
      "issuer_name": "Fidelity National Information Services, Inc.",
      "reporting_owner": "Williams Lenore D",
      "reporting_owner_cik": "0001730708",
      "reporting_owner_position": "CEVP, Chief People Officer",
      "transaction_date": "2024-11-15",
      "transaction_shares": "11305",
      "transaction_price": "87.97",
      "transaction_type": "S",
      "shares_after_transaction": "32198.9308"
    },
    {
      "id": 268847,
      "issuer_name": "Fidelity National Information Services, Inc.",
      "reporting_owner": "Williams Lenore D",
      "reporting_owner_cik": "0001730708",
      "reporting_owner_position": "CEVP, Chief People Officer",
      "transaction_date": "2024-11-15",
      "transaction_shares": "11305",
      "transaction_price": "87.97",
      "transaction_type": "S",
      "shares_after_transaction": "32198.9308"
    },
    {
      "id": 310836,
      "issuer_name": "Fidelity National Information Services, Inc.",
      "reporting_owner": "Williams Lenore D",
      "reporting_owner_cik": "0001730708",
      "reporting_owner_position": "CEVP, Chief People Officer",
      "transaction_date": "2024-11-15",
      "transaction_shares": "11305",
      "transaction_price": "87.97",
      "transaction_type": "S",
      "shares_after_transaction": "32198.9308"
    },
    {
      "id": 168739,
      "issuer_name": "Fidelity National Information Services, Inc.",
      "reporting_owner": "Gibson Kourtney",
      "reporting_owner_cik": "0001818810",
      "reporting_owner_position": null,
      "transaction_date": "2024-11-07",
      "transaction_shares": "1451",
      "transaction_price": "0",
      "transaction_type": "A",
      "shares_after_transaction": "1451"
    },
    {
      "id": 168741,
      "issuer_name": "Fidelity National Information Services, Inc.",
      "reporting_owner": "ANASENES NICOLE",
      "reporting_owner_cik": "0001748987",
      "reporting_owner_position": null,
      "transaction_date": "2024-11-07",
      "transaction_shares": "1658",
      "transaction_price": "0",
      "transaction_type": "A",
      "shares_after_transaction": "1658"
    },
    {
      "id": 199682,
      "issuer_name": "Fidelity National Information Services, Inc.",
      "reporting_owner": "Gibson Kourtney",
      "reporting_owner_cik": "0001818810",
      "reporting_owner_position": null,
      "transaction_date": "2024-11-07",
      "transaction_shares": "1451",
      "transaction_price": "0",
      "transaction_type": "A",
      "shares_after_transaction": "1451"
    },
    {
      "id": 199684,
      "issuer_name": "Fidelity National Information Services, Inc.",
      "reporting_owner": "ANASENES NICOLE",
      "reporting_owner_cik": "0001748987",
      "reporting_owner_position": null,
      "transaction_date": "2024-11-07",
      "transaction_shares": "1658",
      "transaction_price": "0",
      "transaction_type": "A",
      "shares_after_transaction": "1658"
    },
    {
      "id": 232885,
      "issuer_name": "Fidelity National Information Services, Inc.",
      "reporting_owner": "Gibson Kourtney",
      "reporting_owner_cik": "0001818810",
      "reporting_owner_position": null,
      "transaction_date": "2024-11-07",
      "transaction_shares": "1451",
      "transaction_price": "0",
      "transaction_type": "A",
      "shares_after_transaction": "1451"
    },
    {
      "id": 232887,
      "issuer_name": "Fidelity National Information Services, Inc.",
      "reporting_owner": "ANASENES NICOLE",
      "reporting_owner_cik": "0001748987",
      "reporting_owner_position": null,
      "transaction_date": "2024-11-07",
      "transaction_shares": "1658",
      "transaction_price": "0",
      "transaction_type": "A",
      "shares_after_transaction": "1658"
    },
    {
      "id": 268872,
      "issuer_name": "Fidelity National Information Services, Inc.",
      "reporting_owner": "Gibson Kourtney",
      "reporting_owner_cik": "0001818810",
      "reporting_owner_position": null,
      "transaction_date": "2024-11-07",
      "transaction_shares": "1451",
      "transaction_price": "0",
      "transaction_type": "A",
      "shares_after_transaction": "1451"
    },
    {
      "id": 268874,
      "issuer_name": "Fidelity National Information Services, Inc.",
      "reporting_owner": "ANASENES NICOLE",
      "reporting_owner_cik": "0001748987",
      "reporting_owner_position": null,
      "transaction_date": "2024-11-07",
      "transaction_shares": "1658",
      "transaction_price": "0",
      "transaction_type": "A",
      "shares_after_transaction": "1658"
    },
    {
      "id": 310866,
      "issuer_name": "Fidelity National Information Services, Inc.",
      "reporting_owner": "Gibson Kourtney",
      "reporting_owner_cik": "0001818810",
      "reporting_owner_position": null,
      "transaction_date": "2024-11-07",
      "transaction_shares": "1451",
      "transaction_price": "0",
      "transaction_type": "A",
      "shares_after_transaction": "1451"
    },
    {
      "id": 310868,
      "issuer_name": "Fidelity National Information Services, Inc.",
      "reporting_owner": "ANASENES NICOLE",
      "reporting_owner_cik": "0001748987",
      "reporting_owner_position": null,
      "transaction_date": "2024-11-07",
      "transaction_shares": "1658",
      "transaction_price": "0",
      "transaction_type": "A",
      "shares_after_transaction": "1658"
    },
    {
      "id": 140316,
      "issuer_name": "Fidelity National Information Services, Inc.",
      "reporting_owner": "Goldstein Jeffrey A",
      "reporting_owner_cik": "0001375299",
      "reporting_owner_position": null,
      "transaction_date": "2024-10-15",
      "transaction_shares": "626",
      "transaction_price": "88.25",
      "transaction_type": "P",
      "shares_after_transaction": "10397"
    },
    {
      "id": 168730,
      "issuer_name": "Fidelity National Information Services, Inc.",
      "reporting_owner": "Goldstein Jeffrey A",
      "reporting_owner_cik": "0001375299",
      "reporting_owner_position": null,
      "transaction_date": "2024-10-15",
      "transaction_shares": "626",
      "transaction_price": "88.25",
      "transaction_type": "P",
      "shares_after_transaction": "10397"
    },
    {
      "id": 199673,
      "issuer_name": "Fidelity National Information Services, Inc.",
      "reporting_owner": "Goldstein Jeffrey A",
      "reporting_owner_cik": "0001375299",
      "reporting_owner_position": null,
      "transaction_date": "2024-10-15",
      "transaction_shares": "626",
      "transaction_price": "88.25",
      "transaction_type": "P",
      "shares_after_transaction": "10397"
    },
    {
      "id": 232876,
      "issuer_name": "Fidelity National Information Services, Inc.",
      "reporting_owner": "Goldstein Jeffrey A",
      "reporting_owner_cik": "0001375299",
      "reporting_owner_position": null,
      "transaction_date": "2024-10-15",
      "transaction_shares": "626",
      "transaction_price": "88.25",
      "transaction_type": "P",
      "shares_after_transaction": "10397"
    },
    {
      "id": 268863,
      "issuer_name": "Fidelity National Information Services, Inc.",
      "reporting_owner": "Goldstein Jeffrey A",
      "reporting_owner_cik": "0001375299",
      "reporting_owner_position": null,
      "transaction_date": "2024-10-15",
      "transaction_shares": "626",
      "transaction_price": "88.25",
      "transaction_type": "P",
      "shares_after_transaction": "10397"
    },
    {
      "id": 310854,
      "issuer_name": "Fidelity National Information Services, Inc.",
      "reporting_owner": "Goldstein Jeffrey A",
      "reporting_owner_cik": "0001375299",
      "reporting_owner_position": null,
      "transaction_date": "2024-10-15",
      "transaction_shares": "626",
      "transaction_price": "88.25",
      "transaction_type": "P",
      "shares_after_transaction": "10397"
    }
  ]
}