{
  "ticker": "LH",
  "year": 2024,
  "quarter": 4,
  "last_updated": "2025-04-19T09:36:19.551340",
  "count": 23,
  "transactions": [
    {
      "id": 209458,
      "issuer_name": "LABCORP HOLDINGS INC.",
      "reporting_owner": "Gilliland Dwight Gary",
      "reporting_owner_cik": "0001603769",
      "reporting_owner_position": null,
      "transaction_date": "2024-12-02",
      "transaction_shares": "1000",
      "transaction_price": "241.00",
      "transaction_type": "S",
      "shares_after_transaction": "7712"
    },
    {
      "id": 209470,
      "issuer_name": "LABCORP HOLDINGS INC.",
      "reporting_owner": "EISENBERG GLENN A",
      "reporting_owner_cik": "0001222831",
      "reporting_owner_position": "Executive Vice President",
      "transaction_date": "2024-12-02",
      "transaction_shares": "8923",
      "transaction_price": "209.25",
      "transaction_type": "M",
      "shares_after_transaction": "40212"
    },
    {
      "id": 243575,
      "issuer_name": "LABCORP HOLDINGS INC.",
      "reporting_owner": "Gilliland Dwight Gary",
      "reporting_owner_cik": "0001603769",
      "reporting_owner_position": null,
      "transaction_date": "2024-12-02",
      "transaction_shares": "1000",
      "transaction_price": "241.00",
      "transaction_type": "S",
      "shares_after_transaction": "7712"
    },
    {
      "id": 243587,
      "issuer_name": "LABCORP HOLDINGS INC.",
      "reporting_owner": "EISENBERG GLENN A",
      "reporting_owner_cik": "0001222831",
      "reporting_owner_position": "Executive Vice President",
      "transaction_date": "2024-12-02",
      "transaction_shares": "8923",
      "transaction_price": "209.25",
      "transaction_type": "M",
      "shares_after_transaction": "40212"
    },
    {
      "id": 281563,
      "issuer_name": "LABCORP HOLDINGS INC.",
      "reporting_owner": "Gilliland Dwight Gary",
      "reporting_owner_cik": "0001603769",
      "reporting_owner_position": null,
      "transaction_date": "2024-12-02",
      "transaction_shares": "1000",
      "transaction_price": "241.00",
      "transaction_type": "S",
      "shares_after_transaction": "7712"
    },
    {
      "id": 281583,
      "issuer_name": "LABCORP HOLDINGS INC.",
      "reporting_owner": "EISENBERG GLENN A",
      "reporting_owner_cik": "0001222831",
      "reporting_owner_position": "Executive Vice President",
      "transaction_date": "2024-12-02",
      "transaction_shares": "8923",
      "transaction_price": "209.25",
      "transaction_type": "M",
      "shares_after_transaction": "40212"
    },
    {
      "id": 177904,
      "issuer_name": "LABCORP HOLDINGS INC.",
      "reporting_owner": "Summy Amy B.",
      "reporting_owner_cik": "0001805303",
      "reporting_owner_position": "EVP, Chief Marketing Officer",
      "transaction_date": "2024-11-22",
      "transaction_shares": "4015",
      "transaction_price": "168.52",
      "transaction_type": "M",
      "shares_after_transaction": "7990"
    },
    {
      "id": 209482,
      "issuer_name": "LABCORP HOLDINGS INC.",
      "reporting_owner": "Summy Amy B.",
      "reporting_owner_cik": "0001805303",
      "reporting_owner_position": "EVP, Chief Marketing Officer",
      "transaction_date": "2024-11-22",
      "transaction_shares": "4015",
      "transaction_price": "168.52",
      "transaction_type": "M",
      "shares_after_transaction": "7990"
    },
    {
      "id": 243600,
      "issuer_name": "LABCORP HOLDINGS INC.",
      "reporting_owner": "Summy Amy B.",
      "reporting_owner_cik": "0001805303",
      "reporting_owner_position": "EVP, Chief Marketing Officer",
      "transaction_date": "2024-11-22",
      "transaction_shares": "4015",
      "transaction_price": "168.52",
      "transaction_type": "M",
      "shares_after_transaction": "7990"
    },
    {
      "id": 281600,
      "issuer_name": "LABCORP HOLDINGS INC.",
      "reporting_owner": "Summy Amy B.",
      "reporting_owner_cik": "0001805303",
      "reporting_owner_position": "EVP, Chief Marketing Officer",
      "transaction_date": "2024-11-22",
      "transaction_shares": "4015",
      "transaction_price": "168.52",
      "transaction_type": "M",
      "shares_after_transaction": "7990"
    },
    {
      "id": 177896,
      "issuer_name": "LABCORP HOLDINGS INC.",
      "reporting_owner": "van der Vaart Sandra D",
      "reporting_owner_cik": "0001537208",
      "reporting_owner_position": "EVP, Chief Legal Officer",
      "transaction_date": "2024-11-21",
      "transaction_shares": "1000",
      "transaction_price": "239.4187",
      "transaction_type": "S",
      "shares_after_transaction": "2669.847"
    },
    {
      "id": 209474,
      "issuer_name": "LABCORP HOLDINGS INC.",
      "reporting_owner": "van der Vaart Sandra D",
      "reporting_owner_cik": "0001537208",
      "reporting_owner_position": "EVP, Chief Legal Officer",
      "transaction_date": "2024-11-21",
      "transaction_shares": "1000",
      "transaction_price": "239.4187",
      "transaction_type": "S",
      "shares_after_transaction": "2669.847"
    },
    {
      "id": 243592,
      "issuer_name": "LABCORP HOLDINGS INC.",
      "reporting_owner": "van der Vaart Sandra D",
      "reporting_owner_cik": "0001537208",
      "reporting_owner_position": "EVP, Chief Legal Officer",
      "transaction_date": "2024-11-21",
      "transaction_shares": "1000",
      "transaction_price": "239.4187",
      "transaction_type": "S",
      "shares_after_transaction": "2669.847"
    },
    {
      "id": 281590,
      "issuer_name": "LABCORP HOLDINGS INC.",
      "reporting_owner": "van der Vaart Sandra D",
      "reporting_owner_cik": "0001537208",
      "reporting_owner_position": "EVP, Chief Legal Officer",
      "transaction_date": "2024-11-21",
      "transaction_shares": "1000",
      "transaction_price": "239.4187",
      "transaction_type": "S",
      "shares_after_transaction": "2669.847"
    },
    {
      "id": 177851,
      "issuer_name": "LABCORP HOLDINGS INC.",
      "reporting_owner": "Schechter Adam H",
      "reporting_owner_cik": "0001376841",
      "reporting_owner_position": "President & CEO",
      "transaction_date": "2024-11-11",
      "transaction_shares": "6189",
      "transaction_price": "243.47",
      "transaction_type": "S",
      "shares_after_transaction": "87441"
    },
    {
      "id": 209426,
      "issuer_name": "LABCORP HOLDINGS INC.",
      "reporting_owner": "Schechter Adam H",
      "reporting_owner_cik": "0001376841",
      "reporting_owner_position": "President & CEO",
      "transaction_date": "2024-11-11",
      "transaction_shares": "6189",
      "transaction_price": "243.47",
      "transaction_type": "S",
      "shares_after_transaction": "87441"
    },
    {
      "id": 243543,
      "issuer_name": "LABCORP HOLDINGS INC.",
      "reporting_owner": "Schechter Adam H",
      "reporting_owner_cik": "0001376841",
      "reporting_owner_position": "President & CEO",
      "transaction_date": "2024-11-11",
      "transaction_shares": "6189",
      "transaction_price": "243.47",
      "transaction_type": "S",
      "shares_after_transaction": "87441"
    },
    {
      "id": 281507,
      "issuer_name": "LABCORP HOLDINGS INC.",
      "reporting_owner": "Schechter Adam H",
      "reporting_owner_cik": "0001376841",
      "reporting_owner_position": "President & CEO",
      "transaction_date": "2024-11-11",
      "transaction_shares": "6189",
      "transaction_price": "243.47",
      "transaction_type": "S",
      "shares_after_transaction": "87441"
    },
    {
      "id": 148760,
      "issuer_name": "LABCORP HOLDINGS INC.",
      "reporting_owner": "ANDERSON KERRII B",
      "reporting_owner_cik": "0001227159",
      "reporting_owner_position": null,
      "transaction_date": "2024-10-24",
      "transaction_shares": "1000",
      "transaction_price": "230.00",
      "transaction_type": "S",
      "shares_after_transaction": "13722"
    },
    {
      "id": 177860,
      "issuer_name": "LABCORP HOLDINGS INC.",
      "reporting_owner": "ANDERSON KERRII B",
      "reporting_owner_cik": "0001227159",
      "reporting_owner_position": null,
      "transaction_date": "2024-10-24",
      "transaction_shares": "1000",
      "transaction_price": "230.00",
      "transaction_type": "S",
      "shares_after_transaction": "13722"
    },
    {
      "id": 209436,
      "issuer_name": "LABCORP HOLDINGS INC.",
      "reporting_owner": "ANDERSON KERRII B",
      "reporting_owner_cik": "0001227159",
      "reporting_owner_position": null,
      "transaction_date": "2024-10-24",
      "transaction_shares": "1000",
      "transaction_price": "230.00",
      "transaction_type": "S",
      "shares_after_transaction": "13722"
    },
    {
      "id": 243553,
      "issuer_name": "LABCORP HOLDINGS INC.",
      "reporting_owner": "ANDERSON KERRII B",
      "reporting_owner_cik": "0001227159",
      "reporting_owner_position": null,
      "transaction_date": "2024-10-24",
      "transaction_shares": "1000",
      "transaction_price": "230.00",
      "transaction_type": "S",
      "shares_after_transaction": "13722"
    },
    {
      "id": 281522,
      "issuer_name": "LABCORP HOLDINGS INC.",
      "reporting_owner": "ANDERSON KERRII B",
      "reporting_owner_cik": "0001227159",
      "reporting_owner_position": null,
      "transaction_date": "2024-10-24",
      "transaction_shares": "1000",
      "transaction_price": "230.00",
      "transaction_type": "S",
      "shares_after_transaction": "13722"
    }
  ]
}