{
  "ticker": "EG",
  "year": 2024,
  "quarter": 1,
  "last_updated": "2025-04-19T07:17:27.853786",
  "count": 76,
  "transactions": [
    {
      "id": 13885,
      "issuer_name": "EVEREST GROUP, LTD.",
      "reporting_owner": "KARMILOWICZ MIKE",
      "reporting_owner_cik": "0001851941",
      "reporting_owner_position": "EVP,  Pres/CEO Insurance Div",
      "transaction_date": "2024-03-14",
      "transaction_shares": "1521",
      "transaction_price": "386.6453",
      "transaction_type": "A",
      "shares_after_transaction": "13772"
    },
    {
      "id": 13891,
      "issuer_name": "EVEREST GROUP, LTD.",
      "reporting_owner": "WILLIAMSON JAMES ALLAN",
      "reporting_owner_cik": "0001851417",
      "reporting_owner_position": "EVP,  Chief Operating Officer",
      "transaction_date": "2024-03-14",
      "transaction_shares": "1609",
      "transaction_price": "386.6453",
      "transaction_type": "A",
      "shares_after_transaction": "16081"
    },
    {
      "id": 13896,
      "issuer_name": "EVEREST GROUP, LTD.",
      "reporting_owner": "KOCIANCIC MARK",
      "reporting_owner_cik": "0001835214",
      "reporting_owner_position": "EVP & CFO",
      "transaction_date": "2024-03-14",
      "transaction_shares": "2293",
      "transaction_price": "386.6453",
      "transaction_type": "A",
      "shares_after_transaction": "31035"
    },
    {
      "id": 13898,
      "issuer_name": "EVEREST GROUP, LTD.",
      "reporting_owner": "Andrade Juan C",
      "reporting_owner_cik": "0001457231",
      "reporting_owner_position": "President and CEO",
      "transaction_date": "2024-03-14",
      "transaction_shares": "9252",
      "transaction_price": "386.6453",
      "transaction_type": "A",
      "shares_after_transaction": "66189"
    },
    {
      "id": 26640,
      "issuer_name": "EVEREST GROUP, LTD.",
      "reporting_owner": "KARMILOWICZ MIKE",
      "reporting_owner_cik": "0001851941",
      "reporting_owner_position": "EVP,  Pres/CEO Insurance Div",
      "transaction_date": "2024-03-14",
      "transaction_shares": "1521",
      "transaction_price": "386.6453",
      "transaction_type": "A",
      "shares_after_transaction": "13772"
    },
    {
      "id": 26646,
      "issuer_name": "EVEREST GROUP, LTD.",
      "reporting_owner": "WILLIAMSON JAMES ALLAN",
      "reporting_owner_cik": "0001851417",
      "reporting_owner_position": "EVP,  Chief Operating Officer",
      "transaction_date": "2024-03-14",
      "transaction_shares": "1609",
      "transaction_price": "386.6453",
      "transaction_type": "A",
      "shares_after_transaction": "16081"
    },
    {
      "id": 26651,
      "issuer_name": "EVEREST GROUP, LTD.",
      "reporting_owner": "KOCIANCIC MARK",
      "reporting_owner_cik": "0001835214",
      "reporting_owner_position": "EVP & CFO",
      "transaction_date": "2024-03-14",
      "transaction_shares": "2293",
      "transaction_price": "386.6453",
      "transaction_type": "A",
      "shares_after_transaction": "31035"
    },
    {
      "id": 26653,
      "issuer_name": "EVEREST GROUP, LTD.",
      "reporting_owner": "Andrade Juan C",
      "reporting_owner_cik": "0001457231",
      "reporting_owner_position": "President and CEO",
      "transaction_date": "2024-03-14",
      "transaction_shares": "9252",
      "transaction_price": "386.6453",
      "transaction_type": "A",
      "shares_after_transaction": "66189"
    },
    {
      "id": 13869,
      "issuer_name": "EVEREST GROUP, LTD.",
      "reporting_owner": "McNeilage Hazel",
      "reporting_owner_cik": "0001743097",
      "reporting_owner_position": null,
      "transaction_date": "2024-02-29",
      "transaction_shares": "888",
      "transaction_price": "367.04",
      "transaction_type": "A",
      "shares_after_transaction": "2265"
    },
    {
      "id": 13871,
      "issuer_name": "EVEREST GROUP, LTD.",
      "reporting_owner": "Losquadro Geraldine",
      "reporting_owner_cik": "0001609079",
      "reporting_owner_position": null,
      "transaction_date": "2024-02-29",
      "transaction_shares": "888",
      "transaction_price": "367.04",
      "transaction_type": "A",
      "shares_after_transaction": "13843"
    },
    {
      "id": 13872,
      "issuer_name": "EVEREST GROUP, LTD.",
      "reporting_owner": "TARANTO JOSEPH V",
      "reporting_owner_cik": "0001182528",
      "reporting_owner_position": null,
      "transaction_date": "2024-02-29",
      "transaction_shares": "888",
      "transaction_price": "367.04",
      "transaction_type": "A",
      "shares_after_transaction": "293005"
    },
    {
      "id": 13881,
      "issuer_name": "EVEREST GROUP, LTD.",
      "reporting_owner": "GALTNEY WILLIAM F JR",
      "reporting_owner_cik": "0001139501",
      "reporting_owner_position": null,
      "transaction_date": "2024-02-29",
      "transaction_shares": "888",
      "transaction_price": "367.04",
      "transaction_type": "A",
      "shares_after_transaction": "29952"
    },
    {
      "id": 13888,
      "issuer_name": "EVEREST GROUP, LTD.",
      "reporting_owner": "GRAF JOHN A",
      "reporting_owner_cik": "0001236598",
      "reporting_owner_position": null,
      "transaction_date": "2024-02-29",
      "transaction_shares": "888",
      "transaction_price": "367.04",
      "transaction_type": "A",
      "shares_after_transaction": "15642"
    },
    {
      "id": 13889,
      "issuer_name": "EVEREST GROUP, LTD.",
      "reporting_owner": "Amore John J",
      "reporting_owner_cik": "0001559514",
      "reporting_owner_position": null,
      "transaction_date": "2024-02-29",
      "transaction_shares": "888",
      "transaction_price": "367.04",
      "transaction_type": "A",
      "shares_after_transaction": "23186"
    },
    {
      "id": 13893,
      "issuer_name": "EVEREST GROUP, LTD.",
      "reporting_owner": "HARTZBAND MERYL D",
      "reporting_owner_cik": "0001072504",
      "reporting_owner_position": null,
      "transaction_date": "2024-02-29",
      "transaction_shares": "888",
      "transaction_price": "367.04",
      "transaction_type": "A",
      "shares_after_transaction": "9831"
    },
    {
      "id": 13902,
      "issuer_name": "EVEREST GROUP, LTD.",
      "reporting_owner": "Singer Roger M.",
      "reporting_owner_cik": "0001485529",
      "reporting_owner_position": null,
      "transaction_date": "2024-02-29",
      "transaction_shares": "888",
      "transaction_price": "367.04",
      "transaction_type": "A",
      "shares_after_transaction": "17808"
    },
    {
      "id": 26623,
      "issuer_name": "EVEREST GROUP, LTD.",
      "reporting_owner": "McNeilage Hazel",
      "reporting_owner_cik": "0001743097",
      "reporting_owner_position": null,
      "transaction_date": "2024-02-29",
      "transaction_shares": "888",
      "transaction_price": "367.04",
      "transaction_type": "A",
      "shares_after_transaction": "2265"
    },
    {
      "id": 26625,
      "issuer_name": "EVEREST GROUP, LTD.",
      "reporting_owner": "Losquadro Geraldine",
      "reporting_owner_cik": "0001609079",
      "reporting_owner_position": null,
      "transaction_date": "2024-02-29",
      "transaction_shares": "888",
      "transaction_price": "367.04",
      "transaction_type": "A",
      "shares_after_transaction": "13843"
    },
    {
      "id": 26626,
      "issuer_name": "EVEREST GROUP, LTD.",
      "reporting_owner": "TARANTO JOSEPH V",
      "reporting_owner_cik": "0001182528",
      "reporting_owner_position": null,
      "transaction_date": "2024-02-29",
      "transaction_shares": "888",
      "transaction_price": "367.04",
      "transaction_type": "A",
      "shares_after_transaction": "293005"
    },
    {
      "id": 26636,
      "issuer_name": "EVEREST GROUP, LTD.",
      "reporting_owner": "GALTNEY WILLIAM F JR",
      "reporting_owner_cik": "0001139501",
      "reporting_owner_position": null,
      "transaction_date": "2024-02-29",
      "transaction_shares": "888",
      "transaction_price": "367.04",
      "transaction_type": "A",
      "shares_after_transaction": "29952"
    },
    {
      "id": 26643,
      "issuer_name": "EVEREST GROUP, LTD.",
      "reporting_owner": "GRAF JOHN A",
      "reporting_owner_cik": "0001236598",
      "reporting_owner_position": null,
      "transaction_date": "2024-02-29",
      "transaction_shares": "888",
      "transaction_price": "367.04",
      "transaction_type": "A",
      "shares_after_transaction": "15642"
    },
    {
      "id": 26644,
      "issuer_name": "EVEREST GROUP, LTD.",
      "reporting_owner": "Amore John J",
      "reporting_owner_cik": "0001559514",
      "reporting_owner_position": null,
      "transaction_date": "2024-02-29",
      "transaction_shares": "888",
      "transaction_price": "367.04",
      "transaction_type": "A",
      "shares_after_transaction": "23186"
    },
    {
      "id": 26648,
      "issuer_name": "EVEREST GROUP, LTD.",
      "reporting_owner": "HARTZBAND MERYL D",
      "reporting_owner_cik": "0001072504",
      "reporting_owner_position": null,
      "transaction_date": "2024-02-29",
      "transaction_shares": "888",
      "transaction_price": "367.04",
      "transaction_type": "A",
      "shares_after_transaction": "9831"
    },
    {
      "id": 26657,
      "issuer_name": "EVEREST GROUP, LTD.",
      "reporting_owner": "Singer Roger M.",
      "reporting_owner_cik": "0001485529",
      "reporting_owner_position": null,
      "transaction_date": "2024-02-29",
      "transaction_shares": "888",
      "transaction_price": "367.04",
      "transaction_type": "A",
      "shares_after_transaction": "17808"
    },
    {
      "id": 13876,
      "issuer_name": "EVEREST GROUP, LTD.",
      "reporting_owner": "Freiling Robert J",
      "reporting_owner_cik": "0002004304",
      "reporting_owner_position": "SVP&Chief Accounting Officer",
      "transaction_date": "2024-02-28",
      "transaction_shares": "880",
      "transaction_price": "369.5175",
      "transaction_type": "A",
      "shares_after_transaction": "5955"
    },
    {
      "id": 13882,
      "issuer_name": "EVEREST GROUP, LTD.",
      "reporting_owner": "WILLIAMSON JAMES ALLAN",
      "reporting_owner_cik": "0001851417",
      "reporting_owner_position": "EVP,  Chief Operating Officer",
      "transaction_date": "2024-02-28",
      "transaction_shares": "3627",
      "transaction_price": "369.5175",
      "transaction_type": "A",
      "shares_after_transaction": "14472"
    },
    {
      "id": 13884,
      "issuer_name": "EVEREST GROUP, LTD.",
      "reporting_owner": "KOCIANCIC MARK",
      "reporting_owner_cik": "0001835214",
      "reporting_owner_position": "EVP & CFO",
      "transaction_date": "2024-02-28",
      "transaction_shares": "3708",
      "transaction_price": "369.5175",
      "transaction_type": "A",
      "shares_after_transaction": "28742"
    },
    {
      "id": 13890,
      "issuer_name": "EVEREST GROUP, LTD.",
      "reporting_owner": "KARMILOWICZ MIKE",
      "reporting_owner_cik": "0001851941",
      "reporting_owner_position": "EVP,  Pres/CEO Insurance Div",
      "transaction_date": "2024-02-28",
      "transaction_shares": "2539",
      "transaction_price": "369.5175",
      "transaction_type": "A",
      "shares_after_transaction": "12251"
    },
    {
      "id": 13892,
      "issuer_name": "EVEREST GROUP, LTD.",
      "reporting_owner": "Andrade Juan C",
      "reporting_owner_cik": "0001457231",
      "reporting_owner_position": "President and CEO",
      "transaction_date": "2024-02-28",
      "transaction_shares": "8119",
      "transaction_price": "369.5175",
      "transaction_type": "A",
      "shares_after_transaction": "56937"
    },
    {
      "id": 26631,
      "issuer_name": "EVEREST GROUP, LTD.",
      "reporting_owner": "Freiling Robert J",
      "reporting_owner_cik": "0002004304",
      "reporting_owner_position": "SVP&Chief Accounting Officer",
      "transaction_date": "2024-02-28",
      "transaction_shares": "880",
      "transaction_price": "369.5175",
      "transaction_type": "A",
      "shares_after_transaction": "5955"
    },
    {
      "id": 26637,
      "issuer_name": "EVEREST GROUP, LTD.",
      "reporting_owner": "WILLIAMSON JAMES ALLAN",
      "reporting_owner_cik": "0001851417",
      "reporting_owner_position": "EVP,  Chief Operating Officer",
      "transaction_date": "2024-02-28",
      "transaction_shares": "3627",
      "transaction_price": "369.5175",
      "transaction_type": "A",
      "shares_after_transaction": "14472"
    },
    {
      "id": 26639,
      "issuer_name": "EVEREST GROUP, LTD.",
      "reporting_owner": "KOCIANCIC MARK",
      "reporting_owner_cik": "0001835214",
      "reporting_owner_position": "EVP & CFO",
      "transaction_date": "2024-02-28",
      "transaction_shares": "3708",
      "transaction_price": "369.5175",
      "transaction_type": "A",
      "shares_after_transaction": "28742"
    },
    {
      "id": 26645,
      "issuer_name": "EVEREST GROUP, LTD.",
      "reporting_owner": "KARMILOWICZ MIKE",
      "reporting_owner_cik": "0001851941",
      "reporting_owner_position": "EVP,  Pres/CEO Insurance Div",
      "transaction_date": "2024-02-28",
      "transaction_shares": "2539",
      "transaction_price": "369.5175",
      "transaction_type": "A",
      "shares_after_transaction": "12251"
    },
    {
      "id": 26647,
      "issuer_name": "EVEREST GROUP, LTD.",
      "reporting_owner": "Andrade Juan C",
      "reporting_owner_cik": "0001457231",
      "reporting_owner_position": "President and CEO",
      "transaction_date": "2024-02-28",
      "transaction_shares": "8119",
      "transaction_price": "369.5175",
      "transaction_type": "A",
      "shares_after_transaction": "56937"
    },
    {
      "id": 13877,
      "issuer_name": "EVEREST GROUP, LTD.",
      "reporting_owner": "Freiling Robert J",
      "reporting_owner_cik": "0002004304",
      "reporting_owner_position": "SVP&Chief Accounting Officer",
      "transaction_date": "2024-02-27",
      "transaction_shares": "62",
      "transaction_price": "365.6775",
      "transaction_type": "F",
      "shares_after_transaction": "5075"
    },
    {
      "id": 13901,
      "issuer_name": "EVEREST GROUP, LTD.",
      "reporting_owner": "KARMILOWICZ MIKE",
      "reporting_owner_cik": "0001851941",
      "reporting_owner_position": "EVP,  Pres/CEO Insurance Div",
      "transaction_date": "2024-02-27",
      "transaction_shares": "141",
      "transaction_price": "365.6775",
      "transaction_type": "F",
      "shares_after_transaction": "9712"
    },
    {
      "id": 26632,
      "issuer_name": "EVEREST GROUP, LTD.",
      "reporting_owner": "Freiling Robert J",
      "reporting_owner_cik": "0002004304",
      "reporting_owner_position": "SVP&Chief Accounting Officer",
      "transaction_date": "2024-02-27",
      "transaction_shares": "62",
      "transaction_price": "365.6775",
      "transaction_type": "F",
      "shares_after_transaction": "5075"
    },
    {
      "id": 26656,
      "issuer_name": "EVEREST GROUP, LTD.",
      "reporting_owner": "KARMILOWICZ MIKE",
      "reporting_owner_cik": "0001851941",
      "reporting_owner_position": "EVP,  Pres/CEO Insurance Div",
      "transaction_date": "2024-02-27",
      "transaction_shares": "141",
      "transaction_price": "365.6775",
      "transaction_type": "F",
      "shares_after_transaction": "9712"
    },
    {
      "id": 13870,
      "issuer_name": "EVEREST GROUP, LTD.",
      "reporting_owner": "Freiling Robert J",
      "reporting_owner_cik": "0002004304",
      "reporting_owner_position": "SVP&Chief Accounting Officer",
      "transaction_date": "2024-02-26",
      "transaction_shares": "50",
      "transaction_price": "370.055",
      "transaction_type": "F",
      "shares_after_transaction": "5137"
    },
    {
      "id": 13878,
      "issuer_name": "EVEREST GROUP, LTD.",
      "reporting_owner": "Andrade Juan C",
      "reporting_owner_cik": "0001457231",
      "reporting_owner_position": "President and CEO",
      "transaction_date": "2024-02-26",
      "transaction_shares": "693",
      "transaction_price": "370.055",
      "transaction_type": "F",
      "shares_after_transaction": "48818"
    },
    {
      "id": 13886,
      "issuer_name": "EVEREST GROUP, LTD.",
      "reporting_owner": "KARMILOWICZ MIKE",
      "reporting_owner_cik": "0001851941",
      "reporting_owner_position": "EVP,  Pres/CEO Insurance Div",
      "transaction_date": "2024-02-26",
      "transaction_shares": "122",
      "transaction_price": "370.055",
      "transaction_type": "F",
      "shares_after_transaction": "9853"
    },
    {
      "id": 26624,
      "issuer_name": "EVEREST GROUP, LTD.",
      "reporting_owner": "Freiling Robert J",
      "reporting_owner_cik": "0002004304",
      "reporting_owner_position": "SVP&Chief Accounting Officer",
      "transaction_date": "2024-02-26",
      "transaction_shares": "50",
      "transaction_price": "370.055",
      "transaction_type": "F",
      "shares_after_transaction": "5137"
    },
    {
      "id": 26633,
      "issuer_name": "EVEREST GROUP, LTD.",
      "reporting_owner": "Andrade Juan C",
      "reporting_owner_cik": "0001457231",
      "reporting_owner_position": "President and CEO",
      "transaction_date": "2024-02-26",
      "transaction_shares": "693",
      "transaction_price": "370.055",
      "transaction_type": "F",
      "shares_after_transaction": "48818"
    },
    {
      "id": 26641,
      "issuer_name": "EVEREST GROUP, LTD.",
      "reporting_owner": "KARMILOWICZ MIKE",
      "reporting_owner_cik": "0001851941",
      "reporting_owner_position": "EVP,  Pres/CEO Insurance Div",
      "transaction_date": "2024-02-26",
      "transaction_shares": "122",
      "transaction_price": "370.055",
      "transaction_type": "F",
      "shares_after_transaction": "9853"
    },
    {
      "id": 13873,
      "issuer_name": "EVEREST GROUP, LTD.",
      "reporting_owner": "TARANTO JOSEPH V",
      "reporting_owner_cik": "0001182528",
      "reporting_owner_position": null,
      "transaction_date": "2024-02-24",
      "transaction_shares": "108",
      "transaction_price": "370.055",
      "transaction_type": "F",
      "shares_after_transaction": "292209"
    },
    {
      "id": 26627,
      "issuer_name": "EVEREST GROUP, LTD.",
      "reporting_owner": "TARANTO JOSEPH V",
      "reporting_owner_cik": "0001182528",
      "reporting_owner_position": null,
      "transaction_date": "2024-02-24",
      "transaction_shares": "108",
      "transaction_price": "370.055",
      "transaction_type": "F",
      "shares_after_transaction": "292209"
    },
    {
      "id": 13875,
      "issuer_name": "EVEREST GROUP, LTD.",
      "reporting_owner": "KOCIANCIC MARK",
      "reporting_owner_cik": "0001835214",
      "reporting_owner_position": "EVP & CFO",
      "transaction_date": "2024-02-23",
      "transaction_shares": "270",
      "transaction_price": "370.4688",
      "transaction_type": "F",
      "shares_after_transaction": "25463"
    },
    {
      "id": 13880,
      "issuer_name": "EVEREST GROUP, LTD.",
      "reporting_owner": "Freiling Robert J",
      "reporting_owner_cik": "0002004304",
      "reporting_owner_position": "SVP&Chief Accounting Officer",
      "transaction_date": "2024-02-23",
      "transaction_shares": "61",
      "transaction_price": "370.4688",
      "transaction_type": "F",
      "shares_after_transaction": "5305"
    },
    {
      "id": 13894,
      "issuer_name": "EVEREST GROUP, LTD.",
      "reporting_owner": "WILLIAMSON JAMES ALLAN",
      "reporting_owner_cik": "0001851417",
      "reporting_owner_position": "EVP,  Chief Operating Officer",
      "transaction_date": "2024-02-23",
      "transaction_shares": "323",
      "transaction_price": "370.4688",
      "transaction_type": "F",
      "shares_after_transaction": "11426"
    },
    {
      "id": 13897,
      "issuer_name": "EVEREST GROUP, LTD.",
      "reporting_owner": "Andrade Juan C",
      "reporting_owner_cik": "0001457231",
      "reporting_owner_position": "President and CEO",
      "transaction_date": "2024-02-23",
      "transaction_shares": "563",
      "transaction_price": "370.4688",
      "transaction_type": "F",
      "shares_after_transaction": "50657"
    },
    {
      "id": 13899,
      "issuer_name": "EVEREST GROUP, LTD.",
      "reporting_owner": "TARANTO JOSEPH V",
      "reporting_owner_cik": "0001182528",
      "reporting_owner_position": null,
      "transaction_date": "2024-02-23",
      "transaction_shares": "84",
      "transaction_price": "370.4688",
      "transaction_type": "F",
      "shares_after_transaction": "292317"
    },
    {
      "id": 13900,
      "issuer_name": "EVEREST GROUP, LTD.",
      "reporting_owner": "KARMILOWICZ MIKE",
      "reporting_owner_cik": "0001851941",
      "reporting_owner_position": "EVP,  Pres/CEO Insurance Div",
      "transaction_date": "2024-02-23",
      "transaction_shares": "222",
      "transaction_price": "370.4688",
      "transaction_type": "F",
      "shares_after_transaction": "10364"
    },
    {
      "id": 26630,
      "issuer_name": "EVEREST GROUP, LTD.",
      "reporting_owner": "KOCIANCIC MARK",
      "reporting_owner_cik": "0001835214",
      "reporting_owner_position": "EVP & CFO",
      "transaction_date": "2024-02-23",
      "transaction_shares": "270",
      "transaction_price": "370.4688",
      "transaction_type": "F",
      "shares_after_transaction": "25463"
    },
    {
      "id": 26635,
      "issuer_name": "EVEREST GROUP, LTD.",
      "reporting_owner": "Freiling Robert J",
      "reporting_owner_cik": "0002004304",
      "reporting_owner_position": "SVP&Chief Accounting Officer",
      "transaction_date": "2024-02-23",
      "transaction_shares": "61",
      "transaction_price": "370.4688",
      "transaction_type": "F",
      "shares_after_transaction": "5305"
    },
    {
      "id": 26649,
      "issuer_name": "EVEREST GROUP, LTD.",
      "reporting_owner": "WILLIAMSON JAMES ALLAN",
      "reporting_owner_cik": "0001851417",
      "reporting_owner_position": "EVP,  Chief Operating Officer",
      "transaction_date": "2024-02-23",
      "transaction_shares": "323",
      "transaction_price": "370.4688",
      "transaction_type": "F",
      "shares_after_transaction": "11426"
    },
    {
      "id": 26652,
      "issuer_name": "EVEREST GROUP, LTD.",
      "reporting_owner": "Andrade Juan C",
      "reporting_owner_cik": "0001457231",
      "reporting_owner_position": "President and CEO",
      "transaction_date": "2024-02-23",
      "transaction_shares": "563",
      "transaction_price": "370.4688",
      "transaction_type": "F",
      "shares_after_transaction": "50657"
    },
    {
      "id": 26654,
      "issuer_name": "EVEREST GROUP, LTD.",
      "reporting_owner": "TARANTO JOSEPH V",
      "reporting_owner_cik": "0001182528",
      "reporting_owner_position": null,
      "transaction_date": "2024-02-23",
      "transaction_shares": "84",
      "transaction_price": "370.4688",
      "transaction_type": "F",
      "shares_after_transaction": "292317"
    },
    {
      "id": 26655,
      "issuer_name": "EVEREST GROUP, LTD.",
      "reporting_owner": "KARMILOWICZ MIKE",
      "reporting_owner_cik": "0001851941",
      "reporting_owner_position": "EVP,  Pres/CEO Insurance Div",
      "transaction_date": "2024-02-23",
      "transaction_shares": "222",
      "transaction_price": "370.4688",
      "transaction_type": "F",
      "shares_after_transaction": "10364"
    },
    {
      "id": 4350,
      "issuer_name": "EVEREST GROUP, LTD.",
      "reporting_owner": "Singer Roger M.",
      "reporting_owner_cik": "0001485529",
      "reporting_owner_position": null,
      "transaction_date": "2024-02-12",
      "transaction_shares": "500",
      "transaction_price": "357.21",
      "transaction_type": "P",
      "shares_after_transaction": "16920"
    },
    {
      "id": 4354,
      "issuer_name": "EVEREST GROUP, LTD.",
      "reporting_owner": "GRAF JOHN A",
      "reporting_owner_cik": "0001236598",
      "reporting_owner_position": null,
      "transaction_date": "2024-02-12",
      "transaction_shares": "695",
      "transaction_price": "356.75",
      "transaction_type": "P",
      "shares_after_transaction": "14754"
    },
    {
      "id": 13879,
      "issuer_name": "EVEREST GROUP, LTD.",
      "reporting_owner": "Singer Roger M.",
      "reporting_owner_cik": "0001485529",
      "reporting_owner_position": null,
      "transaction_date": "2024-02-12",
      "transaction_shares": "500",
      "transaction_price": "357.21",
      "transaction_type": "P",
      "shares_after_transaction": "16920"
    },
    {
      "id": 13903,
      "issuer_name": "EVEREST GROUP, LTD.",
      "reporting_owner": "GRAF JOHN A",
      "reporting_owner_cik": "0001236598",
      "reporting_owner_position": null,
      "transaction_date": "2024-02-12",
      "transaction_shares": "695",
      "transaction_price": "356.75",
      "transaction_type": "P",
      "shares_after_transaction": "14754"
    },
    {
      "id": 26634,
      "issuer_name": "EVEREST GROUP, LTD.",
      "reporting_owner": "Singer Roger M.",
      "reporting_owner_cik": "0001485529",
      "reporting_owner_position": null,
      "transaction_date": "2024-02-12",
      "transaction_shares": "500",
      "transaction_price": "357.21",
      "transaction_type": "P",
      "shares_after_transaction": "16920"
    },
    {
      "id": 26658,
      "issuer_name": "EVEREST GROUP, LTD.",
      "reporting_owner": "GRAF JOHN A",
      "reporting_owner_cik": "0001236598",
      "reporting_owner_position": null,
      "transaction_date": "2024-02-12",
      "transaction_shares": "695",
      "transaction_price": "356.75",
      "transaction_type": "P",
      "shares_after_transaction": "14754"
    },
    {
      "id": 4349,
      "issuer_name": "EVEREST GROUP, LTD.",
      "reporting_owner": "WILLIAMSON JAMES ALLAN",
      "reporting_owner_cik": "0001851417",
      "reporting_owner_position": "EVP,  Chief Operating Officer",
      "transaction_date": "2024-02-09",
      "transaction_shares": "700",
      "transaction_price": "352.50",
      "transaction_type": "P",
      "shares_after_transaction": "11749"
    },
    {
      "id": 4351,
      "issuer_name": "EVEREST GROUP, LTD.",
      "reporting_owner": "KARMILOWICZ MIKE",
      "reporting_owner_cik": "0001851941",
      "reporting_owner_position": "EVP,  Pres/CEO Insurance Div",
      "transaction_date": "2024-02-09",
      "transaction_shares": "285",
      "transaction_price": "352.3872",
      "transaction_type": "P",
      "shares_after_transaction": "10586"
    },
    {
      "id": 4352,
      "issuer_name": "EVEREST GROUP, LTD.",
      "reporting_owner": "Andrade Juan C",
      "reporting_owner_cik": "0001457231",
      "reporting_owner_position": "President and CEO",
      "transaction_date": "2024-02-09",
      "transaction_shares": "720",
      "transaction_price": "349.72",
      "transaction_type": "P",
      "shares_after_transaction": "51220"
    },
    {
      "id": 4353,
      "issuer_name": "EVEREST GROUP, LTD.",
      "reporting_owner": "KOCIANCIC MARK",
      "reporting_owner_cik": "0001835214",
      "reporting_owner_position": "EVP & CFO",
      "transaction_date": "2024-02-09",
      "transaction_shares": "1000",
      "transaction_price": "349",
      "transaction_type": "P",
      "shares_after_transaction": "25733"
    },
    {
      "id": 13874,
      "issuer_name": "EVEREST GROUP, LTD.",
      "reporting_owner": "WILLIAMSON JAMES ALLAN",
      "reporting_owner_cik": "0001851417",
      "reporting_owner_position": "EVP,  Chief Operating Officer",
      "transaction_date": "2024-02-09",
      "transaction_shares": "700",
      "transaction_price": "352.50",
      "transaction_type": "P",
      "shares_after_transaction": "11749"
    },
    {
      "id": 13883,
      "issuer_name": "EVEREST GROUP, LTD.",
      "reporting_owner": "KARMILOWICZ MIKE",
      "reporting_owner_cik": "0001851941",
      "reporting_owner_position": "EVP,  Pres/CEO Insurance Div",
      "transaction_date": "2024-02-09",
      "transaction_shares": "285",
      "transaction_price": "352.3872",
      "transaction_type": "P",
      "shares_after_transaction": "10586"
    },
    {
      "id": 13887,
      "issuer_name": "EVEREST GROUP, LTD.",
      "reporting_owner": "Andrade Juan C",
      "reporting_owner_cik": "0001457231",
      "reporting_owner_position": "President and CEO",
      "transaction_date": "2024-02-09",
      "transaction_shares": "720",
      "transaction_price": "349.72",
      "transaction_type": "P",
      "shares_after_transaction": "51220"
    },
    {
      "id": 13895,
      "issuer_name": "EVEREST GROUP, LTD.",
      "reporting_owner": "KOCIANCIC MARK",
      "reporting_owner_cik": "0001835214",
      "reporting_owner_position": "EVP & CFO",
      "transaction_date": "2024-02-09",
      "transaction_shares": "1000",
      "transaction_price": "349",
      "transaction_type": "P",
      "shares_after_transaction": "25733"
    },
    {
      "id": 26628,
      "issuer_name": "EVEREST GROUP, LTD.",
      "reporting_owner": "WILLIAMSON JAMES ALLAN",
      "reporting_owner_cik": "0001851417",
      "reporting_owner_position": "EVP,  Chief Operating Officer",
      "transaction_date": "2024-02-09",
      "transaction_shares": "700",
      "transaction_price": "352.50",
      "transaction_type": "P",
      "shares_after_transaction": "11749"
    },
    {
      "id": 26638,
      "issuer_name": "EVEREST GROUP, LTD.",
      "reporting_owner": "KARMILOWICZ MIKE",
      "reporting_owner_cik": "0001851941",
      "reporting_owner_position": "EVP,  Pres/CEO Insurance Div",
      "transaction_date": "2024-02-09",
      "transaction_shares": "285",
      "transaction_price": "352.3872",
      "transaction_type": "P",
      "shares_after_transaction": "10586"
    },
    {
      "id": 26642,
      "issuer_name": "EVEREST GROUP, LTD.",
      "reporting_owner": "Andrade Juan C",
      "reporting_owner_cik": "0001457231",
      "reporting_owner_position": "President and CEO",
      "transaction_date": "2024-02-09",
      "transaction_shares": "720",
      "transaction_price": "349.72",
      "transaction_type": "P",
      "shares_after_transaction": "51220"
    },
    {
      "id": 26650,
      "issuer_name": "EVEREST GROUP, LTD.",
      "reporting_owner": "KOCIANCIC MARK",
      "reporting_owner_cik": "0001835214",
      "reporting_owner_position": "EVP & CFO",
      "transaction_date": "2024-02-09",
      "transaction_shares": "1000",
      "transaction_price": "349",
      "transaction_type": "P",
      "shares_after_transaction": "25733"
    }
  ]
}