{
  "ticker": "TYL",
  "last_updated": "2025-06-12T08:33:44.062300",
  "retention_years": 3,
  "count": 3,
  "transactions": [
    {
      "id": 465,
      "issuer_name": "TYLER TECHNOLOGIES INC",
      "reporting_owner": "MARR JOHN S JR",
      "reporting_owner_cik": "0001085536",
      "reporting_owner_position": "Executive Chair of the Board",
      "transaction_date": "2025-06-09",
      "transaction_shares": "4000",
      "transaction_price": "231.68",
      "transaction_type": "M",
      "shares_after_transaction": "10983"
    },
    {
      "id": 463,
      "issuer_name": "TYLER TECHNOLOGIES INC",
      "reporting_owner": "MILLER BRIAN K",
      "reporting_owner_cik": "0001086072",
      "reporting_owner_position": "Executive VP and CFO",
      "transaction_date": "2025-06-06",
      "transaction_shares": "1200",
      "transaction_price": "577.656",
      "transaction_type": "S",
      "shares_after_transaction": "17475.2913"
    },
    {
      "id": 464,
      "issuer_name": "TYLER TECHNOLOGIES INC",
      "reporting_owner": "Diaz-Pedrosa Abigail Marshall",
      "reporting_owner_cik": "0002069267",
      "reporting_owner_position": "Chief Administrative Officer",
      "transaction_date": "2025-06-05",
      "transaction_shares": "375",
      "transaction_price": "573.6",
      "transaction_type": "S",
      "shares_after_transaction": "247"
    }
  ]
}